odoo/addons/stock_picking_report_valued_sale_mrp/README.rst
odoo/addons/stock_picking_report_valued_sale_mrp/__init__.py
odoo/addons/stock_picking_report_valued_sale_mrp/__manifest__.py
odoo/addons/stock_picking_report_valued_sale_mrp/i18n/stock_picking_report_valued_sale_mrp.pot
odoo/addons/stock_picking_report_valued_sale_mrp/models/__init__.py
odoo/addons/stock_picking_report_valued_sale_mrp/models/stock_move.py
odoo/addons/stock_picking_report_valued_sale_mrp/models/stock_move_line.py
odoo/addons/stock_picking_report_valued_sale_mrp/readme/CONTRIBUTORS.rst
odoo/addons/stock_picking_report_valued_sale_mrp/readme/DESCRIPTION.rst
odoo/addons/stock_picking_report_valued_sale_mrp/readme/ROADMAP.rst
odoo/addons/stock_picking_report_valued_sale_mrp/readme/USAGE.rst
odoo/addons/stock_picking_report_valued_sale_mrp/report/stock_picking_report_valued.xml
odoo/addons/stock_picking_report_valued_sale_mrp/static/description/icon.png
odoo/addons/stock_picking_report_valued_sale_mrp/static/description/index.html
odoo/addons/stock_picking_report_valued_sale_mrp/tests/__init__.py
odoo/addons/stock_picking_report_valued_sale_mrp/tests/test_stock_picking_report_valued_mrp.py
odoo12_addon_stock_picking_report_valued_sale_mrp-12.0.1.0.3.dist-info/METADATA
odoo12_addon_stock_picking_report_valued_sale_mrp-12.0.1.0.3.dist-info/WHEEL
odoo12_addon_stock_picking_report_valued_sale_mrp-12.0.1.0.3.dist-info/top_level.txt
odoo12_addon_stock_picking_report_valued_sale_mrp-12.0.1.0.3.dist-info/RECORD
