Metadata-Version: 2.1
Name: odoo12-addon-stock-picking-report-valued-sale-mrp
Version: 12.0.1.0.3
Summary: Allow to summarize the picking related with the selled kits
Home-page: https://github.com/OCA/stock-logistics-reporting
Author: Tecnativa, Odoo Community Association (OCA)
Author-email: support@odoo-community.org
License: AGPL-3
Platform: UNKNOWN
Classifier: Programming Language :: Python
Classifier: Framework :: Odoo
Classifier: Framework :: Odoo :: 12.0
Classifier: License :: OSI Approved :: GNU Affero General Public License v3
Classifier: Development Status :: 4 - Beta
Requires-Python: >=3.5
Requires-Dist: odoo12-addon-stock-picking-report-valued
Requires-Dist: odoo (<12.1dev,>=12.0a)
